{
  "id": "getting_started",
  "enabled": true,
  "title": {
    "text": "Getting Started",
    "color": "purple"
  },
  "tab_color": "#D49A35",
  "nodes": [
    {
      "id": "get_wood",
      "events": [
        {
          "id": "pickup_logs",
          "type": "item_pickup",
          "item": "#minecraft:logs",
          "count": 1
        }
      ],
      "title": {
        "text": "Get Wood"
      },
      "subtitle": {
        "text": "Punch a tree"
      },
      "description": [
        {
          "text": "Pick up a ",
          "color": "gray"
        },
        {
          "text": "log",
          "color": "gold"
        },
        {
          "text": ". Oak is fine, but any overworld log works.",
          "color": "gray"
        }
      ],
      "icon": {
        "item": "minecraft:oak_log"
      },
      "x": 80,
      "y": 80,
      "shape": "circle",
      "color": "#9B6A3A",
      "parents": []
    },
    {
      "id": "planks",
      "events": [
        {
          "id": "craft_planks",
          "type": "item_craft",
          "item": "#minecraft:planks",
          "count": 4
        }
      ],
      "title": {
        "text": "Craft Planks"
      },
      "subtitle": {
        "text": "Turn logs into building material"
      },
      "description": [
        {
          "text": "Convert logs into ",
          "color": "gray"
        },
        {
          "text": "planks",
          "color": "gold"
        },
        {
          "text": " so you can make a ",
          "color": "gray"
        },
        {
          "text": "crafting table",
          "color": "yellow"
        },
        {
          "text": " and sticks.",
          "color": "gray"
        }
      ],
      "icon": {
        "item": "minecraft:oak_planks"
      },
      "x": 152,
      "y": 35,
      "shape": "square",
      "color": "#B78248",
      "parents": [
        "get_wood"
      ]
    },
    {
      "id": "crafting_table",
      "events": [
        {
          "id": "craft_table",
          "type": "item_craft",
          "item": "minecraft:crafting_table",
          "count": 1
        }
      ],
      "title": {
        "text": "Crafting Table"
      },
      "subtitle": {
        "text": "Unlock the 3x3 grid"
      },
      "description": [
        {
          "text": "Craft a crafting table for tool recipes.",
          "color": "gray"
        }
      ],
      "icon": {
        "item": "minecraft:crafting_table"
      },
      "x": 224,
      "y": 5,
      "shape": "square",
      "color": "#A96F42",
      "parents": [
        "planks"
      ]
    },
    {
      "id": "sticks",
      "events": [
        {
          "id": "craft_sticks",
          "type": "item_craft",
          "item": "minecraft:stick",
          "count": 4
        }
      ],
      "title": {
        "text": "Make Sticks"
      },
      "subtitle": {
        "text": "Tool handles"
      },
      "description": [
        {
          "text": "Craft sticks from planks. You will need them for every early tool tier.",
          "color": "gray"
        }
      ],
      "icon": {
        "item": "minecraft:stick"
      },
      "x": 296,
      "y": 5,
      "shape": "circle",
      "color": "#C79A5A",
      "parents": [
        "crafting_table"
      ]
    },
    {
      "id": "wooden_tools",
      "events": [
        {
          "id": "craft_wooden_pickaxe",
          "type": "item_craft",
          "item": "minecraft:wooden_pickaxe",
          "count": 1
        }
      ],
      "title": {
        "text": "Wooden Tools"
      },
      "subtitle": {
        "text": "Start with a pickaxe"
      },
      "description": [
        {
          "text": "Craft a ",
          "color": "gray"
        },
        {
          "text": "wooden pickaxe",
          "color": "gold"
        },
        {
          "text": ". Other wooden tools are optional, but the pickaxe is the important one.",
          "color": "gray"
        }
      ],
      "icon": {
        "item": "minecraft:wooden_pickaxe"
      },
      "x": 368,
      "y": 35,
      "shape": "diamond",
      "color": "#D2A05D",
      "parents": [
        "sticks"
      ]
    },
    {
      "id": "get_cobble",
      "events": [
        {
          "id": "pickup_cobblestone",
          "type": "item_pickup",
          "item": "minecraft:cobblestone",
          "count": 16
        }
      ],
      "title": {
        "text": "Get Cobble"
      },
      "subtitle": {
        "text": "Mine stone"
      },
      "description": [
        {
          "text": "Use the ",
          "color": "gray"
        },
        {
          "text": "wooden pickaxe",
          "color": "gold"
        },
        {
          "text": " on stone to collect ",
          "color": "gray"
        },
        {
          "text": "cobblestone",
          "color": "aqua"
        },
        {
          "text": ".",
          "color": "gray"
        }
      ],
      "icon": {
        "item": "minecraft:cobblestone"
      },
      "x": 440,
      "y": 80,
      "shape": "square",
      "color": "#A9ADB5",
      "parents": [
        "wooden_tools"
      ]
    },
    {
      "id": "cobble_tools",
      "events": [
        {
          "id": "craft_stone_pickaxe",
          "type": "item_craft",
          "item": "minecraft:stone_pickaxe",
          "count": 1
        }
      ],
      "title": {
        "text": "Cobble Tools"
      },
      "subtitle": {
        "text": "Upgrade to stone"
      },
      "description": [
        {
          "text": "Craft a ",
          "color": "gray"
        },
        {
          "text": "stone pickaxe",
          "color": "aqua"
        },
        {
          "text": " first, then make the other stone tools you want.",
          "color": "gray"
        }
      ],
      "icon": {
        "item": "minecraft:stone_pickaxe"
      },
      "x": 512,
      "y": 35,
      "shape": "diamond",
      "color": "#8F98A3",
      "parents": [
        "get_cobble"
      ]
    },
    {
      "id": "craft_furnace",
      "events": [
        {
          "id": "craft_furnace",
          "type": "item_craft",
          "item": "minecraft:furnace",
          "count": 1
        }
      ],
      "title": {
        "text": "Craft Furnace"
      },
      "subtitle": {
        "text": "Spend eight cobble"
      },
      "description": [
        {
          "text": "Use eight cobblestone to craft a ",
          "color": "gray"
        },
        {
          "text": "furnace",
          "color": "yellow"
        },
        {
          "text": ". This ",
          "color": "gray"
        },
        {
          "text": "branch",
          "color": "green"
        },
        {
          "text": " rejoins when iron is ready to smelt.",
          "color": "gray"
        }
      ],
      "icon": {
        "item": "minecraft:furnace"
      },
      "x": 512,
      "y": 125,
      "shape": "square",
      "color": "#777F8B",
      "parents": [
        "get_cobble"
      ]
    },
    {
      "id": "mine_iron",
      "events": [
        {
          "id": "pickup_raw_iron",
          "type": "item_pickup",
          "item": "minecraft:raw_iron",
          "count": 3
        }
      ],
      "title": {
        "text": "Mine Iron Ore"
      },
      "subtitle": {
        "text": "Stone pickaxe required"
      },
      "description": [
        {
          "text": "Find ",
          "color": "gray"
        },
        {
          "text": "iron ore",
          "color": "red"
        },
        {
          "text": " or deepslate iron ore and mine it with the ",
          "color": "gray"
        },
        {
          "text": "stone pickaxe",
          "color": "aqua"
        },
        {
          "text": ".",
          "color": "gray"
        }
      ],
      "icon": {
        "item": "minecraft:raw_iron"
      },
      "x": 584,
      "y": 35,
      "shape": "circle",
      "color": "#B28A73",
      "parents": [
        "cobble_tools"
      ]
    },
    {
      "id": "smelt_iron",
      "events": [
        {
          "id": "pickup_iron_ingot",
          "type": "item_pickup",
          "item": "minecraft:iron_ingot",
          "count": 3
        }
      ],
      "title": {
        "text": "Get Iron Ingots"
      },
      "subtitle": {
        "text": "Acquire hardware"
      },
      "description": [
        {
          "text": "Smelt ",
          "color": "gray"
        },
        {
          "text": "raw iron",
          "color": "red"
        },
        {
          "text": " into ",
          "color": "gray"
        },
        {
          "text": "iron ingots",
          "color": "white"
        },
        {
          "text": " and pick them up.",
          "color": "gray"
        },
        {
          "text": "\n\nThis node visually joins the furnace and iron-mining branches, but parent links are only guidance.",
          "color": "dark_gray"
        }
      ],
      "icon": {
        "item": "minecraft:iron_ingot"
      },
      "x": 656,
      "y": 80,
      "shape": "diamond",
      "color": "#D4D7DD",
      "parents": [
        "craft_furnace",
        "mine_iron"
      ]
    },
    {
      "id": "iron_pickaxe",
      "events": [
        {
          "id": "craft_iron_pickaxe",
          "type": "item_craft",
          "item": "minecraft:iron_pickaxe",
          "count": 1
        }
      ],
      "title": {
        "text": "Iron Pickaxe"
      },
      "subtitle": {
        "text": "Ready for rarer ores"
      },
      "description": [
        {
          "text": "Craft an ",
          "color": "gray"
        },
        {
          "text": "iron pickaxe",
          "color": "white"
        },
        {
          "text": " so you can mine ",
          "color": "gray"
        },
        {
          "image": "cakequests:textures/quest_images/iron_pickaxe.png"
        },
        {
          "text": "gold",
          "color": "gold"
        },
        {
          "text": ", ",
          "color": "gray"
        },
        {
          "text": "redstone",
          "color": "red"
        },
        {
          "text": ", ",
          "color": "gray"
        },
        {
          "text": "diamond",
          "color": "aqua"
        },
        {
          "text": ", and other harder blocks.",
          "color": "gray"
        }
      ],
      "icon": {
        "item": "minecraft:iron_pickaxe"
      },
      "x": 728,
      "y": 80,
      "shape": "diamond",
      "color": "#C9D0D7",
      "parents": [
        "smelt_iron"
      ]
    }
  ]
}
